{
	"ADMIN_HEADER": "Willkommen im Administrationsbereich",
    "LANGUAGE_SELECT": "Deutsch",
    "NAME": "Name",
    "ENTER_NAME": "Namen eingeben",
    "DESCRIPTION": "Beschreibung",
    "CREATE_EDIT_USER": "Erstelle oder bearbeite Benutzer",
    "MAIL": "Mail",
    "ENTER_MAIL": "Mail eingeben",
    "PASSWORD": "Passwort",
    "ENTER_PASSWORD": "Passwort eingeben",
    "CONFIRM_PASSWORD": "Passwort wiederholen",
    "LANGUAGE": "Sprache",
    "ENTER_LANGUAGE": "Sprache eingeben",
    "ADD_RIGHT": "Recht hinzuf체gen",
    "RIGHT": "Rechte",
    "HAS_ACCESS": "Hat Zugriff",
    "BACK": "Zur체ck",
    "RESET": "Zur체cksetzen",
    "SAVE": "Speichern",
    "ID": "ID",
    "CREATE_EDIT_GROUP": "Gruppe erstellen/bearbeiten",
    "SAVE_RIGHT": "Recht speichern",
    "SELECT_RIGHT": "-- Recht ausw채hlen --",
    "CREATE_EDIT_ROLE": "Rolle erstellen/bearbeiten",
    "MODULE": "Modul",
    "IS_ACTIVE": "Ist aktiviert?"
}